{
  "version": 1,
  "look": "lafayette-square",
  "bbox": {
    "min": [
      -1065,
      0,
      -1065
    ],
    "max": [
      1035,
      0,
      1035
    ]
  },
  "stencil": {
    "center": [
      -15,
      -15
    ],
    "radius": 892,
    "fade": {
      "inner": 758,
      "outer": 892
    },
    "streetFade": {
      "inner": 800,
      "outer": 1000
    }
  },
  "bin": "ground.bin",
  "positionFormat": "float32",
  "indexFormat": "uint32",
  "componentsPerVertex": 3,
  "groups": [
    {
      "kind": "face",
      "id": "residential",
      "color": "#5A8A3A",
      "renderOrder": 0,
      "polygonOffsetUnits": -1,
      "vertexCount": 126325,
      "vertexByteOffset": 0,
      "indexCount": 698088,
      "indexByteOffset": 4580064
    },
    {
      "kind": "face",
      "id": "commercial",
      "color": "#A87D3E",
      "renderOrder": 1,
      "polygonOffsetUnits": -2,
      "vertexCount": 24625,
      "vertexByteOffset": 1515900,
      "indexCount": 133992,
      "indexByteOffset": 7372416
    },
    {
      "kind": "face",
      "id": "vacant",
      "color": "#7A8A4E",
      "renderOrder": 2,
      "polygonOffsetUnits": -3,
      "vertexCount": 7145,
      "vertexByteOffset": 1811400,
      "indexCount": 40512,
      "indexByteOffset": 7908384
    },
    {
      "kind": "face",
      "id": "parking",
      "color": "#6A6A62",
      "renderOrder": 3,
      "polygonOffsetUnits": -4,
      "vertexCount": 28537,
      "vertexByteOffset": 1897140,
      "indexCount": 157149,
      "indexByteOffset": 8070432
    },
    {
      "kind": "face",
      "id": "institutional",
      "color": "#7E8AA8",
      "renderOrder": 4,
      "polygonOffsetUnits": -5,
      "vertexCount": 900,
      "vertexByteOffset": 2239584,
      "indexCount": 4620,
      "indexByteOffset": 8699028
    },
    {
      "kind": "face",
      "id": "recreation",
      "color": "#6EA03E",
      "renderOrder": 5,
      "polygonOffsetUnits": -6,
      "vertexCount": 46264,
      "vertexByteOffset": 2250384,
      "indexCount": 255012,
      "indexByteOffset": 8717508
    },
    {
      "kind": "face",
      "id": "industrial",
      "color": "#8E7060",
      "renderOrder": 6,
      "polygonOffsetUnits": -7,
      "vertexCount": 16538,
      "vertexByteOffset": 2805552,
      "indexCount": 93966,
      "indexByteOffset": 9737556
    },
    {
      "kind": "face",
      "id": "park",
      "color": "#5E8A3A",
      "renderOrder": 7,
      "polygonOffsetUnits": -8,
      "vertexCount": 28875,
      "vertexByteOffset": 3004008,
      "indexCount": 160140,
      "indexByteOffset": 10113420
    },
    {
      "kind": "face",
      "id": "island",
      "color": "#7A7A6E",
      "renderOrder": 8,
      "polygonOffsetUnits": -9,
      "vertexCount": 89,
      "vertexByteOffset": 3350508,
      "indexCount": 255,
      "indexByteOffset": 10753980
    },
    {
      "kind": "face",
      "id": "unknown",
      "color": "#888888",
      "renderOrder": 9,
      "polygonOffsetUnits": -10,
      "vertexCount": 7164,
      "vertexByteOffset": 3351576,
      "indexCount": 38928,
      "indexByteOffset": 10755000
    },
    {
      "kind": "mat",
      "id": "parking_lot",
      "color": "#6A6A62",
      "renderOrder": 10,
      "polygonOffsetUnits": -11,
      "vertexCount": 24781,
      "vertexByteOffset": 3437544,
      "indexCount": 124674,
      "indexByteOffset": 10910712
    },
    {
      "kind": "mat",
      "id": "garden",
      "color": "#7EB04A",
      "renderOrder": 11,
      "polygonOffsetUnits": -12,
      "vertexCount": 4019,
      "vertexByteOffset": 3734916,
      "indexCount": 13215,
      "indexByteOffset": 11409408
    },
    {
      "kind": "mat",
      "id": "playground",
      "color": "#D89A4E",
      "renderOrder": 12,
      "polygonOffsetUnits": -13,
      "vertexCount": 362,
      "vertexByteOffset": 3783144,
      "indexCount": 1416,
      "indexByteOffset": 11462268
    },
    {
      "kind": "mat",
      "id": "swimming_pool",
      "color": "#4A7EB0",
      "renderOrder": 13,
      "polygonOffsetUnits": -14,
      "vertexCount": 56,
      "vertexByteOffset": 3787488,
      "indexCount": 132,
      "indexByteOffset": 11467932
    },
    {
      "kind": "mat",
      "id": "pitch",
      "color": "#5E9E4A",
      "renderOrder": 14,
      "polygonOffsetUnits": -15,
      "vertexCount": 162,
      "vertexByteOffset": 3788160,
      "indexCount": 672,
      "indexByteOffset": 11468460
    },
    {
      "kind": "mat",
      "id": "sports_centre",
      "color": "#6EA05E",
      "renderOrder": 15,
      "polygonOffsetUnits": -16,
      "vertexCount": 181,
      "vertexByteOffset": 3790104,
      "indexCount": 822,
      "indexByteOffset": 11471148
    },
    {
      "kind": "mat",
      "id": "wood",
      "color": "#3E5E2E",
      "renderOrder": 16,
      "polygonOffsetUnits": -17,
      "vertexCount": 4341,
      "vertexByteOffset": 3792276,
      "indexCount": 21813,
      "indexByteOffset": 11474436
    },
    {
      "kind": "mat",
      "id": "scrub",
      "color": "#6E7A4A",
      "renderOrder": 17,
      "polygonOffsetUnits": -18,
      "vertexCount": 574,
      "vertexByteOffset": 3844368,
      "indexCount": 2238,
      "indexByteOffset": 11561688
    },
    {
      "kind": "mat",
      "id": "treelawn:residential",
      "color": "#5A8A3A",
      "renderOrder": 18,
      "polygonOffsetUnits": -19,
      "vertexCount": 1123,
      "vertexByteOffset": 3851256,
      "indexCount": 2775,
      "indexByteOffset": 11570640
    },
    {
      "kind": "mat",
      "id": "treelawn:commercial",
      "color": "#A87D3E",
      "renderOrder": 19,
      "polygonOffsetUnits": -20,
      "vertexCount": 303,
      "vertexByteOffset": 3864732,
      "indexCount": 747,
      "indexByteOffset": 11581740
    },
    {
      "kind": "mat",
      "id": "treelawn:vacant",
      "color": "#7A8A4E",
      "renderOrder": 20,
      "polygonOffsetUnits": -21,
      "vertexCount": 4,
      "vertexByteOffset": 3868368,
      "indexCount": 6,
      "indexByteOffset": 11584728
    },
    {
      "kind": "mat",
      "id": "treelawn:parking",
      "color": "#6A6A62",
      "renderOrder": 21,
      "polygonOffsetUnits": -22,
      "vertexCount": 358,
      "vertexByteOffset": 3868416,
      "indexCount": 918,
      "indexByteOffset": 11584752
    },
    {
      "kind": "mat",
      "id": "treelawn:recreation",
      "color": "#6EA03E",
      "renderOrder": 22,
      "polygonOffsetUnits": -23,
      "vertexCount": 417,
      "vertexByteOffset": 3872712,
      "indexCount": 981,
      "indexByteOffset": 11588424
    },
    {
      "kind": "mat",
      "id": "treelawn:industrial",
      "color": "#8E7060",
      "renderOrder": 23,
      "polygonOffsetUnits": -24,
      "vertexCount": 59,
      "vertexByteOffset": 3877716,
      "indexCount": 153,
      "indexByteOffset": 11592348
    },
    {
      "kind": "mat",
      "id": "treelawn:park",
      "color": "#5E8A3A",
      "renderOrder": 24,
      "polygonOffsetUnits": -25,
      "vertexCount": 114,
      "vertexByteOffset": 3878424,
      "indexCount": 258,
      "indexByteOffset": 11592960
    },
    {
      "kind": "mat",
      "id": "treelawn:unknown",
      "color": "#888888",
      "renderOrder": 25,
      "polygonOffsetUnits": -26,
      "vertexCount": 92,
      "vertexByteOffset": 3879792,
      "indexCount": 192,
      "indexByteOffset": 11593992
    },
    {
      "kind": "mat",
      "id": "treelawn",
      "color": "#5E8A3A",
      "renderOrder": 26,
      "polygonOffsetUnits": -27,
      "vertexCount": 1255,
      "vertexByteOffset": 3880896,
      "indexCount": 3255,
      "indexByteOffset": 11594760
    },
    {
      "kind": "mat",
      "id": "sidewalk",
      "color": "#B8B2A4",
      "renderOrder": 27,
      "polygonOffsetUnits": -28,
      "vertexCount": 8685,
      "vertexByteOffset": 3895956,
      "indexCount": 20475,
      "indexByteOffset": 11607780
    },
    {
      "kind": "mat",
      "id": "curb",
      "color": "#A8826A",
      "renderOrder": 28,
      "polygonOffsetUnits": -29,
      "vertexCount": 16693,
      "vertexByteOffset": 4000176,
      "indexCount": 49851,
      "indexByteOffset": 11689680
    },
    {
      "kind": "mat",
      "id": "highway",
      "color": "#2D2D2C",
      "renderOrder": 29,
      "polygonOffsetUnits": -30,
      "vertexCount": 1040,
      "vertexByteOffset": 4200492,
      "indexCount": 2418,
      "indexByteOffset": 11889084
    },
    {
      "kind": "mat",
      "id": "asphalt",
      "color": "#4A4A48",
      "renderOrder": 30,
      "polygonOffsetUnits": -31,
      "vertexCount": 10368,
      "vertexByteOffset": 4212972,
      "indexCount": 26139,
      "indexByteOffset": 11898756
    },
    {
      "kind": "mat",
      "id": "alley",
      "color": "#3E3E3C",
      "renderOrder": 31,
      "polygonOffsetUnits": -32,
      "vertexCount": 1736,
      "vertexByteOffset": 4337388,
      "indexCount": 4572,
      "indexByteOffset": 12003312
    },
    {
      "kind": "mat",
      "id": "footway",
      "color": "#9A8E78",
      "renderOrder": 32,
      "polygonOffsetUnits": -33,
      "vertexCount": 2036,
      "vertexByteOffset": 4358220,
      "indexCount": 5784,
      "indexByteOffset": 12021600
    },
    {
      "kind": "mat",
      "id": "cycleway",
      "color": "#6EA070",
      "renderOrder": 33,
      "polygonOffsetUnits": -34,
      "vertexCount": 205,
      "vertexByteOffset": 4382652,
      "indexCount": 573,
      "indexByteOffset": 12044736
    },
    {
      "kind": "mat",
      "id": "steps",
      "color": "#A0907E",
      "renderOrder": 34,
      "polygonOffsetUnits": -35,
      "vertexCount": 230,
      "vertexByteOffset": 4385112,
      "indexCount": 594,
      "indexByteOffset": 12047028
    },
    {
      "kind": "mat",
      "id": "path",
      "color": "#8E7E68",
      "renderOrder": 35,
      "polygonOffsetUnits": -36,
      "vertexCount": 143,
      "vertexByteOffset": 4387872,
      "indexCount": 393,
      "indexByteOffset": 12049404
    },
    {
      "kind": "mat",
      "id": "fence",
      "color": "#8A7E6E",
      "renderOrder": 36,
      "polygonOffsetUnits": -37,
      "vertexCount": 4602,
      "vertexByteOffset": 4389588,
      "indexCount": 10140,
      "indexByteOffset": 12050976
    },
    {
      "kind": "mat",
      "id": "wall",
      "color": "#9A8E7E",
      "renderOrder": 37,
      "polygonOffsetUnits": -38,
      "vertexCount": 368,
      "vertexByteOffset": 4444812,
      "indexCount": 774,
      "indexByteOffset": 12091536
    },
    {
      "kind": "mat",
      "id": "retaining_wall",
      "color": "#7A6E5E",
      "renderOrder": 38,
      "polygonOffsetUnits": -39,
      "vertexCount": 500,
      "vertexByteOffset": 4449228,
      "indexCount": 1206,
      "indexByteOffset": 12094632
    },
    {
      "kind": "mat",
      "id": "hedge",
      "color": "#4E6E3E",
      "renderOrder": 39,
      "polygonOffsetUnits": -40,
      "vertexCount": 74,
      "vertexByteOffset": 4455228,
      "indexCount": 174,
      "indexByteOffset": 12099456
    },
    {
      "kind": "mat",
      "id": "edgeline",
      "color": "#E8E4DE",
      "renderOrder": 40,
      "polygonOffsetUnits": -41,
      "vertexCount": 7356,
      "vertexByteOffset": 4456116,
      "indexCount": 19122,
      "indexByteOffset": 12100152
    },
    {
      "kind": "mat",
      "id": "bikelane",
      "color": "#5EA070",
      "renderOrder": 41,
      "polygonOffsetUnits": -42,
      "vertexCount": 620,
      "vertexByteOffset": 4544388,
      "indexCount": 1560,
      "indexByteOffset": 12176640
    },
    {
      "kind": "mat",
      "id": "stripe",
      "color": "#F2CE4A",
      "renderOrder": 42,
      "polygonOffsetUnits": -43,
      "vertexCount": 2353,
      "vertexByteOffset": 4551828,
      "indexCount": 6051,
      "indexByteOffset": 12182880
    }
  ]
}